robotdesigner/__init__.py
robotdesigner/addrviz.bash
robotdesigner/colconbuildws.bash
robotdesigner/createpackage.bash
robotdesigner/createws.bash
robotdesigner/destroypackage.bash
robotdesigner/main.py
robotdesigner/new_implement.py
robotdesigner/new_test.py
robotdesigner/urdf.py
robotdesigner/view.rviz
robotdesigner/write_launch.py
robotdesigner/write_setup.py
robotdesigner-0.1.0.dist-info/LICENSE
robotdesigner-0.1.0.dist-info/METADATA
robotdesigner-0.1.0.dist-info/WHEEL
robotdesigner-0.1.0.dist-info/RECORD
